spotiply/__init__.py
spotiply/client.py
spotiply/exceptions.py
spotiply/oauth.py
spotiply-1.0.0.dist-info/LICENSE
spotiply-1.0.0.dist-info/METADATA
spotiply-1.0.0.dist-info/WHEEL
spotiply-1.0.0.dist-info/top_level.txt
spotiply-1.0.0.dist-info/RECORD
