Metadata-Version: 2.1
Name: spotiply
Version: 1.0.0
Summary: A Python Library for Spotify Web API. This is a self project while expanding my knowledge in Python.
Home-page: https://github.com/muggleboii/spotify
Author: muggleboii
Author-email: francisgian.fgm@gmail.com
License: UNKNOWN
Platform: UNKNOWN
Requires-Python: >=3.6
Requires-Dist: requests (==2.24.0)
